{
  "id": "doc_0097",
  "title": "台风\"奥鹿\"在安徽省登陆 最大风力10级",
  "content": "2024年11月11日，今年第24号台风\"奥鹿\"在安徽省黄山市沿海登陆，登陆时中心附近最大风力10级（62米/秒），中心最低气压950百帕。受台风影响，安徽省沿海地区出现暴雨到大暴雨，局部特大暴雨，最大累计降雨量达187毫米。台风造成83人遇难、8人失踪、283人受伤，紧急转移安置17.6万人，直接经济损失约116.7亿元。绿舟救援队已启动I级应急响应，民政部提前部署防台风工作。目前台风已减弱为热带低压，但后续降雨仍需警惕。",
  "url": "https://disaster-news.example.com/article/doc_0097",
  "date": "2024-11-11",
  "disaster_type": "台风",
  "images": [],
  "ground_truth": {
    "disaster_type": "台风",
    "event_time": "2024年11月11日",
    "event_location": "安徽省黄山市",
    "response_level": "I级",
    "rescue_org": [
      "绿舟救援队",
      "民政部"
    ],
    "casualties": "遇难83人，受伤283人",
    "economic_loss": "116.7亿元"
  },
  "crawl_time": "2026-03-08 21:10:08"
}