{
  "title": "让名著从高高在上到亲近鲜活，名家领读为孩子们种下阅读的种子 _光明网",
  "content": "https://flv1.gmw.cn/gma/20260512/20260512154843554_4502.mp4\n【悦读同行·育见美好】\n编者按：\n书籍是人类智慧的结晶，是人类进步的阶梯。首个“全民阅读活动周”之际，我们特别推出“悦读同行·育见美好”专栏，聚焦书香校园建设热点议题，对话作家、校长、教师及出版界人士，力求以多元视角与一线实践，呈现全民阅读时代背景下，书香校园建设的生动图景与深层思考。\n本期对话：学而思教育集团党委书记、执行总裁 位晨\n“这些传承百年、千年、历经岁月沉淀的名著，对于十年后乃至更远的年轻人和孩子们来说，依然充满魅力，值得去阅读。”日前，在“名家领读名著”少年儿童阅读活动中，学而思教育集团党委书记、执行总裁位晨这样阐述名著的魅力。\n在她看来，当孩子们在“名家领读”过程中听到名家亲自讲述创作故事、深入浅出地解读经典，那些原本高高在上的名著便会变得可亲可感，枯燥的文字也随之鲜活起来。位晨介绍，学而思大阅读体系多年来深耕少儿阅读领域，致力于将优质资源、科学方法与经典图书整合起来，送到孩子们手中，得到了广大家长与孩子们的认可。\n“阅读这件事，急不得，也慢不得。”她解释说，“急不得”，是因为孩子的成长自有其节奏；“慢不得”，则是因为童年的阅读时光弥足珍贵。“我们希望尽早为孩子们打开那扇通往阅读的大门，让更多孩子在名家引领下走进名著的世界，在那里发现智慧，收获成长，找到属于自己的精神家园。”位晨期待与更多名家携手，为孩子们种下阅读的种子，并陪伴它生根、发芽，长成参天大树。\n光明网微光工作室出品\n记者邱晓琴 张晓荣\n责编：杨帆\n阅读剩余全文（",
  "url": "https://edu.gmw.cn/2026-05/13/content_38760762.htm",
  "date": "2026-05-13",
  "images": [
    {
      "src": "C:\\Users\\Administrator\\Desktop\\大三下\\信息与知识获取\\作业2-信息检索系统\\data\\images\\129809697aeb.jpg",
      "alt": "",
      "original_src": "https://img.gmw.cn/pic/gmwLogo_share.jpg"
    },
    {
      "src": "C:\\Users\\Administrator\\Desktop\\大三下\\信息与知识获取\\作业2-信息检索系统\\data\\images\\96d92efcdd9f.png",
      "alt": "",
      "original_src": "https://img.gmw.cn/pic/mgmw/pengyouquan.png"
    },
    {
      "src": "C:\\Users\\Administrator\\Desktop\\大三下\\信息与知识获取\\作业2-信息检索系统\\data\\images\\d833f1096ac3.png",
      "alt": "",
      "original_src": "https://img.gmw.cn/pic/mgmw/layershare.png"
    },
    {
      "src": "C:\\Users\\Administrator\\Desktop\\大三下\\信息与知识获取\\作业2-信息检索系统\\data\\images\\8050bd58aabb.png",
      "alt": "",
      "original_src": "https://img.gmw.cn/pic/mgmw/arrow.png"
    }
  ],
  "source": "光明网",
  "category": "综合",
  "content_length": 690,
  "image_count": 9,
  "id": "doc_e5a074f03024",
  "crawl_time": "2026-06-05 18:05:17",
  "local_images": [
    {
      "local_path": "C:\\Users\\Administrator\\Desktop\\大三下\\信息与知识获取\\作业2-信息检索系统\\data\\images\\129809697aeb.jpg",
      "original_src": "https://img.gmw.cn/pic/gmwLogo_share.jpg",
      "alt": ""
    },
    {
      "local_path": "C:\\Users\\Administrator\\Desktop\\大三下\\信息与知识获取\\作业2-信息检索系统\\data\\images\\96d92efcdd9f.png",
      "original_src": "https://img.gmw.cn/pic/mgmw/pengyouquan.png",
      "alt": ""
    },
    {
      "local_path": "C:\\Users\\Administrator\\Desktop\\大三下\\信息与知识获取\\作业2-信息检索系统\\data\\images\\d833f1096ac3.png",
      "original_src": "https://img.gmw.cn/pic/mgmw/layershare.png",
      "alt": ""
    },
    {
      "local_path": "C:\\Users\\Administrator\\Desktop\\大三下\\信息与知识获取\\作业2-信息检索系统\\data\\images\\8050bd58aabb.png",
      "original_src": "https://img.gmw.cn/pic/mgmw/arrow.png",
      "alt": ""
    }
  ]
}