{
  "title": "美媒：全球南方国家加速拥抱清洁能源 中国制造提供重要支撑-中新网",
  "content": "2026年06月05日 17:02　来源：总台环球资讯广播\n全球媒体聚焦 | 美媒：全球南方国家加速拥抱清洁能源 中国制造提供重要支撑\n美国《外交政策》网站近日刊文称，美伊冲突爆发后，国际油气价格上涨，给许多依赖能源进口的发展中国家带来现实压力。正是在这一背景下，全球南方国家加速拥抱清洁能源。\n清洁能源不仅是气候议题还是发展议题\n过去，太阳能、风能、电池储能和电动汽车，更多被视为应对气候变化、减少碳排放的长期方案。如今，在许多全球南方国家，清洁能源正在成为降低外部能源依赖、增强能源自主能力的现实选择。\n文章指出，全球清洁能源转型本就具备经济基础。2025年，全球清洁能源投资达到创纪录的2.2万亿美元，是化石燃料投资的两倍。2024年，全球新投产的大型可再生能源项目中，91%的发电成本已经低于最便宜的新建化石燃料发电项目。与此同时，电池储能成本自2010年以来下降93%，让太阳能和风能在电力系统中的实用性进一步提升。\n这种成本优势，正在加速向发展中国家扩散。\n中国制造成为全球南方能源转型重要支撑\n文章指出，2024年，中国对发展中经济体的太阳能产品出口已经超过对发达经济体的出口。同年，巴基斯坦进口约17吉瓦中国太阳能组件，规模几乎相当于其并网电力容量的一半。在印度尼西亚、泰国和墨西哥，价格较低的中国制造电动汽车，已经接近最便宜燃油车的价格水平。\n印尼总统普拉博沃在东盟峰会上表示，在中东局势动荡背景下，能源依赖“不再是长期问题，而是紧迫问题”。印尼国家电力公司随后启动1225兆瓦大型太阳能项目招标，并推动新的国家太阳能目标。孟加拉国电力发展委员会也在4月发布495兆瓦并网太阳能项目招标。印度、越南等国也在推进太阳能、可再生能源和替代液化天然气项目。\n文章称，这些项目并非在当前危机爆发后才突然出现。大型能源投资往往需要多年准备。但本轮能源冲击，正在改变这些项目的战略意义，也在推动审批和落地提速。\n在交通领域，全球南方国家同样在加速转向清洁化。智利为购买电动汽车的出租车司机提供优惠信贷，柬埔寨下调电动汽车进口税，老挝降低燃油消费税。对这些国家而言，交通电气化不仅意味着未来减排，也可以缓解油价波动带来的压力。\n文章认为，当前国际能源价格波动，正在推动全球南方国家重新思考能源安全与发展道路，加速拥抱清洁能源。\n来源 | 总台环球资讯\n编译 | 李修莉\n签审 | 贾延宁\n监制 | 邹浩宇",
  "url": "https://www.chinanews.com.cn/gj/2026/06-05/10634874.shtml",
  "date": "2026-06-05",
  "images": [
    {
      "src": "C:\\Users\\Administrator\\Desktop\\大三下\\信息与知识获取\\作业2-信息检索系统\\data\\images\\e93993d46c32.png",
      "alt": "中国新闻网",
      "original_src": "https://www.chinanews.com.cn/fileftp/2025/07/2025-07-17/U947P4T47D55580F24532DT20250717134135.png"
    },
    {
      "src": "C:\\Users\\Administrator\\Desktop\\大三下\\信息与知识获取\\作业2-信息检索系统\\data\\images\\96acfdf97999.png",
      "alt": "",
      "original_src": "https://image.cns.com.cn/2022homepage/images/toparr.png"
    },
    {
      "src": "C:\\Users\\Administrator\\Desktop\\大三下\\信息与知识获取\\作业2-信息检索系统\\data\\images\\b622753eb5aa.png",
      "alt": "",
      "original_src": "https://www.chinanews.com.cn/fileftp/2022/05/2022-05-09/U435P4T47D50136F24533DT20220510101956.png"
    },
    {
      "src": "C:\\Users\\Administrator\\Desktop\\大三下\\信息与知识获取\\作业2-信息检索系统\\data\\images\\a89701025be4.jpg",
      "alt": "",
      "original_src": "https://image.cns.com.cn/default/5ddb9ec3/20210728/qw.jpg"
    },
    {
      "src": "C:\\Users\\Administrator\\Desktop\\大三下\\信息与知识获取\\作业2-信息检索系统\\data\\images\\98b2d651009d.jpg",
      "alt": "",
      "original_src": "https://image.cns.com.cn/default/5ddb9ec3/20210728/jw.jpg"
    }
  ],
  "source": "中国新闻网",
  "category": "财经",
  "content_length": 1004,
  "image_count": 10,
  "id": "doc_18093d4a34f7",
  "crawl_time": "2026-06-05 18:05:01",
  "local_images": [
    {
      "local_path": "C:\\Users\\Administrator\\Desktop\\大三下\\信息与知识获取\\作业2-信息检索系统\\data\\images\\e93993d46c32.png",
      "original_src": "https://www.chinanews.com.cn/fileftp/2025/07/2025-07-17/U947P4T47D55580F24532DT20250717134135.png",
      "alt": "中国新闻网"
    },
    {
      "local_path": "C:\\Users\\Administrator\\Desktop\\大三下\\信息与知识获取\\作业2-信息检索系统\\data\\images\\96acfdf97999.png",
      "original_src": "https://image.cns.com.cn/2022homepage/images/toparr.png",
      "alt": ""
    },
    {
      "local_path": "C:\\Users\\Administrator\\Desktop\\大三下\\信息与知识获取\\作业2-信息检索系统\\data\\images\\b622753eb5aa.png",
      "original_src": "https://www.chinanews.com.cn/fileftp/2022/05/2022-05-09/U435P4T47D50136F24533DT20220510101956.png",
      "alt": ""
    },
    {
      "local_path": "C:\\Users\\Administrator\\Desktop\\大三下\\信息与知识获取\\作业2-信息检索系统\\data\\images\\a89701025be4.jpg",
      "original_src": "https://image.cns.com.cn/default/5ddb9ec3/20210728/qw.jpg",
      "alt": ""
    },
    {
      "local_path": "C:\\Users\\Administrator\\Desktop\\大三下\\信息与知识获取\\作业2-信息检索系统\\data\\images\\98b2d651009d.jpg",
      "original_src": "https://image.cns.com.cn/default/5ddb9ec3/20210728/jw.jpg",
      "alt": ""
    }
  ]
}