{
  "title": "牢记初心使命 奋进复兴征程丨嘉兴：革命红船起航地 共富实干谱新篇-新华网",
  "content": "6月1日，游客在嘉兴南湖湖心岛瞻仰红船。新华社记者 韩传号 摄\n新华社杭州6月4日电\n题：嘉兴：革命红船起航地 共富实干谱新篇\n开栏的话：今年是中国共产党成立105周年。百余年前，革命先辈高举信仰火炬，点燃华夏大地的燎原星火，开启为中国人民谋幸福、为中华民族谋复兴的壮阔征程。栉风沐雨，初心历久弥坚；蝶变焕新，红色热土书写时代华章。\n从即日起，新华社开设“牢记初心使命 奋进复兴征程”专栏，探访革命圣地，感受红色沃土从烽火岁月到锦绣今朝的变迁，全景式展现在中国共产党领导下各地攻坚克难、富民兴业的非凡成就。\n新华社记者胡了然、唐弢\n105年前，浙江嘉兴南湖的一艘小小红船，见证了中国共产党的诞生，孕育了开天辟地、敢为人先的首创精神，坚定理想、百折不挠的奋斗精神，立党为公、忠诚为民的奉献精神。\n正如习近平总书记所指出的：“上海党的一大会址、嘉兴南湖红船是我们党梦想起航的地方。我们党从这里诞生，从这里出征，从这里走向全国执政。这里是我们党的根脉。”\n今天，传承红船精神，以城乡共富夯实根基，以科技首创赋能升级，在高质量发展建设共同富裕示范区中勇当先行者，新时代的嘉禾大地尽显勃勃生机。\n红船精神铸新魂\n嘉兴南湖，红船静静泊于碧波之上。\n1921年夏，中国共产党第一次全国代表大会在上海秘密召开，会议由于受到巡捕的袭扰被迫中断，代表们辗转至此，完成会议议程。\n“在嘉兴短短半天时间的会议当中，完成了最重要的建党议程，会议通过了中国共产党的第一个纲领、第一个决议，选举产生了党的中央领导机构，正式宣告了中国共产党的诞生。”南湖革命纪念馆馆长吴建华说，这正是嘉兴作为中国革命红船起航地的历史意义所在。\n时代变迁，精神永恒。\n嘉兴火车站前的新时代“重走一大路”红色旅游线路游客中心（6月1日摄）。新华社记者 韩传号 摄\n如今，新时代“重走一大路”研学精品线路串联起百年红色坐标，无数游客追寻着先辈的足迹，感悟初心使命。\n6月1日，少先队红领巾讲解员高晴萱在嘉兴南湖革命纪念馆内接受采访。新华社记者 韩传号 摄\n在南湖革命纪念馆内，一批批少先队红领巾讲解员接过宣讲接力棒，用清脆童声娓娓讲述百年党史。这座纪念馆2006年6月28日由时任浙江省委书记习近平亲自奠基，2011年纪念建党90周年前夕落成开放。\n“每一次讲解，都像与革命先辈对话，让我倍感光荣。”小讲解员莫景铄说。\n目前，“红船小讲解”已有570多名市级核心队员，累计讲解2800多次，服务听众超34万人次，成为嘉兴红色旅游的一道亮丽风景。\n城乡共富谱新篇\n红船精神的火种，化作“敢为人先”的基因，流淌进嘉兴的城乡血脉，驱动着一场深刻的共富实践。\n6月1日，嘉兴市南湖区凤桥镇三星村村民在种植葡萄的温室大棚内进行田间管理。新华社记者 韩传号 摄\n初夏的嘉兴南湖区凤桥镇三星村，千亩桃林枝繁叶茂、满目生机，整洁的步道纵横交错，现代化民居整齐林立。\n曾经的三星村，村民生计仅靠传统生猪散养和零散水蜜桃种植，产业链条短，发展一度陷入瓶颈。\n三星村村两委带领村民打破守旧思维和发展桎梏，借着“千万工程”东风，全村上下聚力人居环境提质、盘活闲置资源、升级特色产业。\n三星村党委书记徐利军说：“我们深耕千亩桃林的生态资源，将桃林变景点、农房变客房，打造赏花采摘、乡村研学、民宿体验等多元新业态。”单一季节性果林产业转化为农文旅全域融合发展新图景。\n如今，三星村已成为远近闻名的网红共富村。“2025年，村集体经济收入同比增长23.63%，人均可支配收入达6.2万元。”徐利军说。\n近年来，嘉兴持续统筹盘活乡村人、地、产、景等各类资源。通过多元业态激活村庄经营，全方位推动城乡功能互补和城乡一体化协同发展。\n农村居民人均可支配收入绝对值已连续22年居全省首位；城乡居民收入比缩小至1.48∶1，连续7年保持全省最优水平；嘉兴已成为全国城乡融合程度最深、城乡差别最小的城市之一……“均衡富庶”成为嘉兴令人称道的标签，更是嘉兴阔步发展的民生底气。\n嘉兴航空物流枢纽项目之一的圆通东方天地港自动化传送带上的快递（6月2日摄）。新华社记者 韩传号 摄\n敢为人先闯新程\n走进浙江清华长三角研究院的成果展厅，一系列“硬科技”令人眼前一亮：载重百公斤的无人机用微型燃气轮机、高精度“电子皮肤”、正在多模态采集数据的具身机器人……这些成果正加速从实验室走向生产线。\n浙江清华长三角研究院展厅内展示的超薄柔性芯片（6月1日摄）。新华社记者 韩传号 摄\n作为浙江首个省校共建的新型创新载体，浙江清华长三角研究院像一座桥梁，一头连接科技创新，一头直面广阔市场。“这里的科研成果，从实验室到生产线，最快只用几个月。”浙江清华长三角研究院党委书记、院长黄开胜说，高效的成果转化机制，让科创价值快速赋能实体经济。\n嘉兴持续扎根长三角科创沃土，不断突破路径依赖，深耕新质生产力培育。\n一个个创新策源地的涌现，催生着一派欣欣向荣的科创生态——\n嘉善祥符荡率先探索跨区域协同创新机制，成长为长三角生态绿色一体化发展示范区的科创高地，吸引一大批高端科研院所、未来实验室和前沿项目在此驻扎；“乌镇之光”超算中心前瞻布局，如今已成为拥有每秒181.9千万亿次计算能力的国家级超算中心，大幅降低了区域中小企业的创新成本；“亚太路科创带”串联多座科创平台，打通研发、孵化、产业化全链条，实现了从传统农业向现代产业体系的跨越……\n“十四五”以来，嘉兴科创实力持续跃升，连续三年捧回“浙江制造天工鼎”；2025年全社会研发投入占GDP比重达3.57%，位列全省第二；创新指数、科技成果转化指数均居全省前列……\n从平台集聚、技术攻关到成果转化、产业迭代，嘉兴依托红船精神持续破局开路，以科创升级为共富之路注入强劲动力。",
  "url": "https://www.news.cn/politics/20260604/511457272ed84e72a8b744983ace88e2/c.html",
  "date": "2006-06-28",
  "images": [
    {
      "src": "C:\\Users\\Administrator\\Desktop\\大三下\\信息与知识获取\\作业2-信息检索系统\\data\\images\\86aa1086071d.png",
      "alt": "",
      "original_src": "https://www.news.cn/detail2020/images/ewm.png"
    },
    {
      "src": "C:\\Users\\Administrator\\Desktop\\大三下\\信息与知识获取\\作业2-信息检索系统\\data\\images\\90e046c047b3.png",
      "alt": "",
      "original_src": "https://www.news.cn/2021detail/images/qrcode-app.png"
    },
    {
      "src": "C:\\Users\\Administrator\\Desktop\\大三下\\信息与知识获取\\作业2-信息检索系统\\data\\images\\90e046c047b3.png",
      "alt": "",
      "original_src": "https://www.news.cn/2021detail/images/qrcode-app.png"
    }
  ],
  "source": "新华网",
  "category": "综合",
  "content_length": 2352,
  "image_count": 10,
  "id": "doc_8c17c2335b59",
  "crawl_time": "2026-06-05 18:05:32",
  "local_images": [
    {
      "local_path": "C:\\Users\\Administrator\\Desktop\\大三下\\信息与知识获取\\作业2-信息检索系统\\data\\images\\86aa1086071d.png",
      "original_src": "https://www.news.cn/detail2020/images/ewm.png",
      "alt": ""
    },
    {
      "local_path": "C:\\Users\\Administrator\\Desktop\\大三下\\信息与知识获取\\作业2-信息检索系统\\data\\images\\90e046c047b3.png",
      "original_src": "https://www.news.cn/2021detail/images/qrcode-app.png",
      "alt": ""
    },
    {
      "local_path": "C:\\Users\\Administrator\\Desktop\\大三下\\信息与知识获取\\作业2-信息检索系统\\data\\images\\90e046c047b3.png",
      "original_src": "https://www.news.cn/2021detail/images/qrcode-app.png",
      "alt": ""
    }
  ]
}