{
  "title": "菲律宾粤商总会会长林翰：联动侨团资源 双向赋能川渝产业落地东南亚-中新网",
  "content": "中新网\n重庆6月5日电(陈媛)“当前，中国与菲律宾的贸易正从传统的商品互通，加速迈向产业共建、产能合作与双向投资的深层次阶段。”5日，菲律宾粤商总会会长林翰在重庆接受\n中新网\n采访时表示，未来将充分发挥侨商纽带作用，推动中国西部地区优质产业资源精准落地东南亚市场。\n2000年，林翰前往菲律宾创业，敏锐捕捉到当地新能源产业的市场机遇，后逐步将商业版图拓展至跨境贸易、房地产开发等多个领域。如今，他依托商会和侨联平台，常态化开展侨胞联络、新生代侨商培育及双向招商工作，精准赋能地方侨务，助力粤港澳大湾区及西部地区的对外开放与跨境经贸合作发展。\n近年来，中国与东盟经贸合作展现出蓬勃活力。2025年，双边贸易总额突破1万亿美元；同年10月，川渝携手赴新加坡招商引资，这是成渝地区双城经济圈深化对外开放、主动对接东盟市场，并融入全球产业链供应链的关键一步。\n“依托成渝地区双城经济圈和西部陆海新通道，中国西部地区已然成为我国向南开放、链接东盟市场的关键枢纽。”林翰表示，在本次大会上，重点关注特色农产品跨境贸易、装备制造与新能源产业对接、跨境产业园区共建三大领域。\n在林翰看来，川渝地区不仅拥有便捷的南向物流通道，还具备丰富的农林资源和完备的制造业体系，是支撑中国深化与东南亚合作的坚实产业腹地。他期待川渝地区能进一步畅通南向开放通道，完善涉外营商环境配套，搭建常态化的政企侨商对接机制。\n针对未来的发展方向，林翰建议，川渝地区应持续放大通道、产业与资源三大优势，坚持“以侨为桥、以商促通、以产促合”，常态化开展与东南亚的产业对接、海外市场布局及人文交流互鉴，共同打造西部南向开放合作的新高地。\n“我们将以菲律宾为核心支点，联动东盟各国侨团资源，复制推广成熟的经贸与侨务合作模式。”林翰表示，未来将聚焦农产品、新能源、装备制造及跨境电商等重点赛道，通过双向资源引流与赋能，持续深化中国与东盟民间的经贸往来与人文交流，实现真正的互利共赢。(完)",
  "url": "https://www.chinanews.com.cn/aseaninfo/2026/06-05/10634788.shtml",
  "date": "2026-06-05",
  "images": [
    {
      "src": "C:\\Users\\Administrator\\Desktop\\大三下\\信息与知识获取\\作业2-信息检索系统\\data\\images\\e93993d46c32.png",
      "alt": "中国新闻网",
      "original_src": "https://www.chinanews.com.cn/fileftp/2025/07/2025-07-17/U947P4T47D55580F24532DT20250717134135.png"
    },
    {
      "src": "C:\\Users\\Administrator\\Desktop\\大三下\\信息与知识获取\\作业2-信息检索系统\\data\\images\\96acfdf97999.png",
      "alt": "",
      "original_src": "https://image.cns.com.cn/2022homepage/images/toparr.png"
    },
    {
      "src": "C:\\Users\\Administrator\\Desktop\\大三下\\信息与知识获取\\作业2-信息检索系统\\data\\images\\b622753eb5aa.png",
      "alt": "",
      "original_src": "https://www.chinanews.com.cn/fileftp/2022/05/2022-05-09/U435P4T47D50136F24533DT20220510101956.png"
    },
    {
      "src": "C:\\Users\\Administrator\\Desktop\\大三下\\信息与知识获取\\作业2-信息检索系统\\data\\images\\a89701025be4.jpg",
      "alt": "",
      "original_src": "https://image.cns.com.cn/default/5ddb9ec3/20210728/qw.jpg"
    },
    {
      "src": "C:\\Users\\Administrator\\Desktop\\大三下\\信息与知识获取\\作业2-信息检索系统\\data\\images\\98b2d651009d.jpg",
      "alt": "",
      "original_src": "https://image.cns.com.cn/default/5ddb9ec3/20210728/jw.jpg"
    }
  ],
  "source": "中国新闻网",
  "category": "财经",
  "content_length": 818,
  "image_count": 10,
  "id": "doc_b9506655f403",
  "crawl_time": "2026-06-05 18:04:58",
  "local_images": [
    {
      "local_path": "C:\\Users\\Administrator\\Desktop\\大三下\\信息与知识获取\\作业2-信息检索系统\\data\\images\\e93993d46c32.png",
      "original_src": "https://www.chinanews.com.cn/fileftp/2025/07/2025-07-17/U947P4T47D55580F24532DT20250717134135.png",
      "alt": "中国新闻网"
    },
    {
      "local_path": "C:\\Users\\Administrator\\Desktop\\大三下\\信息与知识获取\\作业2-信息检索系统\\data\\images\\96acfdf97999.png",
      "original_src": "https://image.cns.com.cn/2022homepage/images/toparr.png",
      "alt": ""
    },
    {
      "local_path": "C:\\Users\\Administrator\\Desktop\\大三下\\信息与知识获取\\作业2-信息检索系统\\data\\images\\b622753eb5aa.png",
      "original_src": "https://www.chinanews.com.cn/fileftp/2022/05/2022-05-09/U435P4T47D50136F24533DT20220510101956.png",
      "alt": ""
    },
    {
      "local_path": "C:\\Users\\Administrator\\Desktop\\大三下\\信息与知识获取\\作业2-信息检索系统\\data\\images\\a89701025be4.jpg",
      "original_src": "https://image.cns.com.cn/default/5ddb9ec3/20210728/qw.jpg",
      "alt": ""
    },
    {
      "local_path": "C:\\Users\\Administrator\\Desktop\\大三下\\信息与知识获取\\作业2-信息检索系统\\data\\images\\98b2d651009d.jpg",
      "original_src": "https://image.cns.com.cn/default/5ddb9ec3/20210728/jw.jpg",
      "alt": ""
    }
  ]
}