{
  "title": "优质美育下基层 音乐润育青少年--教育--人民网",
  "content": "人民网北京6月3日电 （记者郝孟佳）近日，“授渔计划·央音1+N”2026全国乡村音乐美育浸润实践活动在全国15个区县市同步开展。活动通过为期五天的沉浸式美育赋能、课堂教研及成果展演，让艺术教育资源扎根基层校园。\n活动现场。主办方供图\n据介绍，本次活动覆盖中小学全学段，共走进全国70余所乡村中小学。各高校的美育专家与青年教研团队以专业授课、教师研修、节目创编、成果汇演等多元形式，精准赋能基层美育教学，搭建起高校引领、政企联动、校地协同、全国共建的美育新平台。\n活动现场。主办方供图\n各地汇演节目形式丰富，涵盖民乐合奏、红色戏剧、诗歌朗诵、歌舞合唱、双语展演、地方特色非遗等。从经典民乐《茉莉花》的清雅悠扬，到双语戏剧《觉醒年代》的热血赤诚；从展现各地奋进发展精神的情景剧，到致敬山河盛世、礼赞百年征程、传承长征精神的合唱曲目。每一个节目均由高校专家全程指导、师生精心打磨。\n据悉，本次活动由中央音乐学院等单位联合举办。活动期间，累计超过2000名音乐骨干教师参与现场研学与交流切磋。",
  "url": "http://edu.people.com.cn/n1/2026/0603/c1006-40733218.html",
  "date": "2026-06-03",
  "images": [
    {
      "src": "C:\\Users\\Administrator\\Desktop\\大三下\\信息与知识获取\\作业2-信息检索系统\\data\\images\\61873714bb5a.jpg",
      "alt": "",
      "original_src": "http://world.people.com.cn/img/2020peopleindex/img/logo_share_ap.jpg"
    },
    {
      "src": "C:\\Users\\Administrator\\Desktop\\大三下\\信息与知识获取\\作业2-信息检索系统\\data\\images\\2374227cbb99.png",
      "alt": "人民网",
      "original_src": "http://edu.people.com.cn/img/2020wbc/imgs/logo.png"
    }
  ],
  "source": "人民网",
  "category": "综合",
  "content_length": 443,
  "image_count": 10,
  "id": "doc_b95e8b35a04b",
  "crawl_time": "2026-06-05 18:03:45",
  "local_images": [
    {
      "local_path": "C:\\Users\\Administrator\\Desktop\\大三下\\信息与知识获取\\作业2-信息检索系统\\data\\images\\61873714bb5a.jpg",
      "original_src": "http://world.people.com.cn/img/2020peopleindex/img/logo_share_ap.jpg",
      "alt": ""
    },
    {
      "local_path": "C:\\Users\\Administrator\\Desktop\\大三下\\信息与知识获取\\作业2-信息检索系统\\data\\images\\2374227cbb99.png",
      "original_src": "http://edu.people.com.cn/img/2020wbc/imgs/logo.png",
      "alt": "人民网"
    }
  ]
}