{
  "id": "doc_0011",
  "title": "问答系统：自然语言处理领域的前沿方向",
  "content": "近年来，问答系统作为自然语言处理领域的重要研究方向，受到了学术界和产业界的广泛关注。研究人员通过改进语义理解和分词算法等关键技术，在跨语言交流、法律文书分析等应用场景中取得了显著突破。据统计，过去一年中相关论文发表量增长了50%，多家知名企业加大了在该领域的研发投入。专家指出，问答系统技术的成熟将极大推动自然语言处理的产业化进程，预计未来三到五年内，该技术将在智能写作等领域实现大规模商用。同时，需要关注技术发展带来的伦理、隐私和安全挑战。",
  "url": "https://tech.example.com/article/0011",
  "date": "2026-01-05",
  "images": [
    {
      "src": "https://picsum.photos/seed/11/400/300",
      "alt": "自然语言处理-问答系统示意图"
    }
  ],
  "crawl_time": "2026-03-08 20:18:20"
}